<root>
    <marker>
        <timecode>00:00:00:00</timecode>
        <title>Inizio</title>
        <longitude>12.469686</longitude>
        <latitude>45.469182</latitude>
    </marker>
    <marker>
        <timecode>00:00:20:12</timecode>
        <title>title</title>
        <longitude>12.475387</longitude>
        <latitude>45.473831</latitude>
    </marker>
    <marker>
        <timecode>00:00:38:17</timecode>
        <title>dovrebbe funzionare</title>
        <longitude>12.476022</longitude>
        <latitude>45.475455</latitude>
    </marker>
    <marker>
        <timecode>00:00:46:06</timecode>
        <title>questo no</title>
        <longitude>12.4791479</longitude>
        <latitude>45.4779235</latitude>
    </marker>
    <marker>
        <timecode>00:00:57:06</timecode>
        <title>questo di nuovo si</title>
        <longitude>12.480724</longitude>
        <latitude>45.479783</latitude>
    </marker>
    <marker>
        <timecode>00:01:17:04</timecode>
        <title>title</title>
        <longitude>12.481131</longitude>
        <latitude>45.481608</latitude>
    </marker>
    <marker>
        <timecode>00:01:27:08</timecode>
        <title>title</title>
        <longitude>12.481531</longitude>
        <latitude>45.483315</latitude>
    </marker>
    <marker>
        <timecode>00:01:36:22</timecode>
        <title>curvone a dx</title>
        <longitude>12.483250</longitude>
        <latitude>45.489358</latitude>
    </marker>
    <marker>
        <timecode>00:01:45:11</timecode>
        <title>title</title>
        <longitude>12.491556</longitude>
        <latitude>45.490155</latitude>
    </marker>
    <marker>
        <timecode>00:01:55:19</timecode>
        <title>title</title>
        <longitude>12.502613</longitude>
        <latitude>45.491147</latitude>
    </marker>
    <marker>
        <timecode>00:02:14:13</timecode>
        <title>fine prima parte</title>
        <longitude>12.504445</longitude>
        <latitude>45.491385</latitude>
    </marker>
    <marker>
        <timecode>00:02:33:13</timecode>
        <title>inizio seconda parte</title>
        <longitude>12.487715</longitude>
        <latitude>45.491796</latitude>
    </marker>
    <marker>
        <timecode>00:02:46:02</timecode>
        <title>title</title>
        <longitude>12.484633</longitude>
        <latitude>45.492931</latitude>
    </marker>
    <marker>
        <timecode>00:02:59:00</timecode>
        <title>title</title>
        <longitude>12.485052</longitude>
        <latitude>45.494961</latitude>
    </marker>
    <marker>
        <timecode>00:03:11:14</timecode>
        <title>title</title>
        <longitude>12.485832</longitude>
        <latitude>45.497316</latitude>
    </marker>
    <marker>
        <timecode>00:03:37:06</timecode>
        <title>title</title>
        <longitude>12.489509</longitude>
        <latitude>45.498267</latitude>
    </marker>
    <marker>
        <timecode>00:03:50:08</timecode>
        <title>title</title>
        <longitude>12.493020</longitude>
        <latitude>45.497800</latitude>
    </marker>
    <marker>
        <timecode>00:04:02:15</timecode>
        <title>title</title>
        <longitude>12.495729</longitude>
        <latitude>45.496751</latitude>
    </marker>
    <marker>
        <timecode>00:04:16:03</timecode>
        <title>title</title>
        <longitude>12.498293</longitude>
        <latitude>45.496983</latitude>
    </marker>
    <marker>
        <timecode>00:04:28:08</timecode>
        <title>title</title>
        <longitude>12.501144</longitude>
        <latitude>45.496327</latitude>
    </marker>
    <marker>
        <timecode>00:04:41:16</timecode>
        <title>title</title>
        <longitude>12.502566</longitude>
        <latitude>45.494861</latitude>
    </marker>
    <marker>
        <timecode>00:04:47:07</timecode>
        <title>title</title>
        <longitude>12.505571</longitude>
        <latitude>45.492913</latitude>
    </marker>
    <marker>
        <timecode>00:04:53:23</timecode>
        <title>title</title>
        <longitude>12.506657</longitude>
        <latitude>45.492354</latitude>
    </marker>
</root>